{"GlobalPropertiesHash":"J4FRXNBmLXxty/NUGDQHkF/L4G/ygQdnOmTPo4F3G28=","FingerprintPatternsHash":"gq3WsqcKBUGTSNle7RKKyXRIwh7M8ccEqOqYvIzoM04=","PropertyOverridesHash":"8ZRc1sGeVrPBx4lD717BgRaQekyh78QKV9SKsdt638U=","InputHashes":["KaZzLg3m9XwThTC/XI4tkrRvImMjx8OhrFV56MfAUkY=","FR3dbXbhq01aYD/tpjsLtpXOoEqLS03qHoq2UfkxPuk=","Kc84HXRBszQSSuhx2kPj\u002BdCjpnuIek8tc59eL7SPM6I=","n5lXB9eEfZqRWg0mmIF0wCf7L\u002BJlPyZDF0Job0vrfcU=","8jtI1tW35vwt6knNbHEQV2pwN7tx/l0ab1uosmcrrrc=","n6Lie8MBwDuCSTgT9iZX7sw\u002Bv6RqSqjHJoDoM1tp0yo=","g5l7uZuCWTEhSH7yjma4hqv2mxWRsb/slvVAjFRyDdo=","0nGuzkQyBrALhPlZNzwT6CP3vYIwKFF01NeY843K4Ag=","21uI\u002BTsLoHRZd/yv8iPQkxgUnB6MOQlw34TcOXfHWhw=","/yg5kvApZe6SUc5BhiCilVZ5pleMkWAZYt\u002BbeEaWyrI=","XKyyegcONtlf2X54g3C3NJmKRA5okf3xX7ULwJMdxo0=","tTIbKlO47az9eOpKI/iwVH8JeDWycPt\u002BKqHaitBpjBc=","hhtFmXQjBMv1ysnOtiFS7Cm\u002Bl6AWpyB4yfh9hCJ0GmE=","pEp\u002BFtHzWxPsGCFEElw3vHfup\u002BfxIlcI4UViQJDXZFU=","vSRXzXYZ/paTT8yVE6beemvNf6JREIOR00YLn8YpD5Y=","bZ5nJYlXk56sV4trt5J/86BpEw47uTc6tdS9D67cu/E=","vtII5a3Nojrry/56QLJD9EOYLBucEaVcTbrkIOqfMQo=","TeufzEjiwkCaFFiCly\u002BL\u002BOD8auMN3JRGazXYpTiJICQ=","guTTbUCtb3NV0ajsGem9uz5DqEZM/thja\u002BderJjO9NY=","soFw9plcFFe3Mu5FN20JcfN\u002BH2ViaWLLbcDcg6/qHEI=","5a11oMpcG5Dpn0FvgiFoyUu/abSPnCzihq1aDQy164Q=","igl2w8xVaEqVhQDBFeDFyi9mU0RKGLH/lXr1OdzgpdU=","jxSn2xrtuung2iP561BFOjEkS98\u002BbnuLDIgZLYOymTw=","/69SKJfc4aDVDN8chS8tvX4\u002Bjs8a781bzt/l2RERIKs=","VCeENDIVZ1UoX0UjE\u002BQZnrnWv/gsR6UZcXfenPzwPCY=","qHp9NhkNmLQiKv\u002BC3F0XjSyUsD3SApG9hemSApgCX/k=","qRFrYpEBJqFQl\u002BtXJxjSYY4e/345DW5ts6n8tByAREk=","\u002BlDbtM7\u002BRVdb22UdVGKeY12UO15PhgevqDtRAwyJeyA=","QUAoNOxytg/ky\u002Brb0c5JZFEKTpmZg9Oyyq45pkWsqhA=","2FbD7LNGvEmjmofP0lyzHDacYiHJpSbALzEcGML9aHc=","CzjDlRQ6sCkVhr3tHDQwDVsh\u002BLanxP7ou8jxesT5gV8=","5aWQQd8w5D4sIbGs/gGTEYVIWYuPnqbZY6xBWjJg1VM=","6Y4ReZGrDKBZTmW8r90XeDjGiI4/qKvNqCdnaoXAH1Q=","Tr8/hPYessA6TcrhcAFq02SfKKfdLCHBHj16gj\u002BU5jM=","xrVjS54Zx4QxJf6ez5yNIMa01umuEAQ6kVGjBl8SlI8=","Cz\u002BqE/572HrGOA1WsWAlrZowH0rs3O3Dl6bWJczW0EI=","pjCCSJ26Ismbfs57Rg75LodaCTtcpmPppBzqVnS7eNc=","yK2vfGMcuw5OxXY23ZgPQxIpkds\u002B6HUTnK5oKTNh2Wg="],"CachedAssets":{"KaZzLg3m9XwThTC/XI4tkrRvImMjx8OhrFV56MfAUkY=":{"Identity":"C:\\Users\\phamn\\Desktop\\Code\\TrungWebAPI\\src\\WebApp\\wwwroot\\assets\\favicon.ico","SourceId":"WebApp","SourceType":"Discovered","ContentRoot":"C:\\Users\\phamn\\Desktop\\Code\\TrungWebAPI\\src\\WebApp\\wwwroot\\","BasePath":"/","RelativePath":"assets/favicon#[.{fingerprint}]?.ico","AssetKind":"All","AssetMode":"All","AssetRole":"Primary","AssetMergeBehavior":null,"AssetMergeSource":"","RelatedAsset":null,"AssetTraitName":null,"AssetTraitValue":null,"Fingerprint":"devepoo3hg","Integrity":"ixBg8ZN2jFW8SN7ei6jam\u002BbJP45tyulG428aiVa3Jps=","CopyToOutputDirectory":"Never","CopyToPublishDirectory":"PreserveNewest","OriginalItemSpec":"wwwroot\\assets\\favicon.ico","FileLength":23462,"LastWriteTime":"2023-12-06T10:46:11+00:00"},"FR3dbXbhq01aYD/tpjsLtpXOoEqLS03qHoq2UfkxPuk=":{"Identity":"C:\\Users\\phamn\\Desktop\\Code\\TrungWebAPI\\src\\WebApp\\wwwroot\\assets\\img\\about-bg.jpg","SourceId":"WebApp","SourceType":"Discovered","ContentRoot":"C:\\Users\\phamn\\Desktop\\Code\\TrungWebAPI\\src\\WebApp\\wwwroot\\","BasePath":"/","RelativePath":"assets/img/about-bg#[.{fingerprint}]?.jpg","AssetKind":"All","AssetMode":"All","AssetRole":"Primary","AssetMergeBehavior":null,"AssetMergeSource":"","RelatedAsset":null,"AssetTraitName":null,"AssetTraitValue":null,"Fingerprint":"jiyb00j17u","Integrity":"e/NzqEQENvdHeLv9bK\u002BbyRplQRtYIrS00bMhb7kw738=","CopyToOutputDirectory":"Never","CopyToPublishDirectory":"PreserveNewest","OriginalItemSpec":"wwwroot\\assets\\img\\about-bg.jpg","FileLength":2547880,"LastWriteTime":"2023-12-06T10:46:11+00:00"},"Kc84HXRBszQSSuhx2kPj\u002BdCjpnuIek8tc59eL7SPM6I=":{"Identity":"C:\\Users\\phamn\\Desktop\\Code\\TrungWebAPI\\src\\WebApp\\wwwroot\\assets\\img\\contact-bg.jpg","SourceId":"WebApp","SourceType":"Discovered","ContentRoot":"C:\\Users\\phamn\\Desktop\\Code\\TrungWebAPI\\src\\WebApp\\wwwroot\\","BasePath":"/","RelativePath":"assets/img/contact-bg#[.{fingerprint}]?.jpg","AssetKind":"All","AssetMode":"All","AssetRole":"Primary","AssetMergeBehavior":null,"AssetMergeSource":"","RelatedAsset":null,"AssetTraitName":null,"AssetTraitValue":null,"Fingerprint":"71ge1jjbx4","Integrity":"VfplT6bFmd\u002BKV6GhO0U2W2lUGpiHfTA4Sfpbv43hbww=","CopyToOutputDirectory":"Never","CopyToPublishDirectory":"PreserveNewest","OriginalItemSpec":"wwwroot\\assets\\img\\contact-bg.jpg","FileLength":500680,"LastWriteTime":"2023-12-06T10:46:11+00:00"},"n5lXB9eEfZqRWg0mmIF0wCf7L\u002BJlPyZDF0Job0vrfcU=":{"Identity":"C:\\Users\\phamn\\Desktop\\Code\\TrungWebAPI\\src\\WebApp\\wwwroot\\assets\\img\\home-bg.jpg","SourceId":"WebApp","SourceType":"Discovered","ContentRoot":"C:\\Users\\phamn\\Desktop\\Code\\TrungWebAPI\\src\\WebApp\\wwwroot\\","BasePath":"/","RelativePath":"assets/img/home-bg#[.{fingerprint}]?.jpg","AssetKind":"All","AssetMode":"All","AssetRole":"Primary","AssetMergeBehavior":null,"AssetMergeSource":"","RelatedAsset":null,"AssetTraitName":null,"AssetTraitValue":null,"Fingerprint":"gszixjpvae","Integrity":"sMKZCWajLb8/5O1/K6/NN0KOmAjGYJUOZscKgIqrarQ=","CopyToOutputDirectory":"Never","CopyToPublishDirectory":"PreserveNewest","OriginalItemSpec":"wwwroot\\assets\\img\\home-bg.jpg","FileLength":1007801,"LastWriteTime":"2023-12-06T10:46:11+00:00"},"8jtI1tW35vwt6knNbHEQV2pwN7tx/l0ab1uosmcrrrc=":{"Identity":"C:\\Users\\phamn\\Desktop\\Code\\TrungWebAPI\\src\\WebApp\\wwwroot\\assets\\img\\post-bg.jpg","SourceId":"WebApp","SourceType":"Discovered","ContentRoot":"C:\\Users\\phamn\\Desktop\\Code\\TrungWebAPI\\src\\WebApp\\wwwroot\\","BasePath":"/","RelativePath":"assets/img/post-bg#[.{fingerprint}]?.jpg","AssetKind":"All","AssetMode":"All","AssetRole":"Primary","AssetMergeBehavior":null,"AssetMergeSource":"","RelatedAsset":null,"AssetTraitName":null,"AssetTraitValue":null,"Fingerprint":"90he4bzuxx","Integrity":"mY11p7VWsxBhKdWcwU/UAyVSJehRzy/6VS8mZqb437g=","CopyToOutputDirectory":"Never","CopyToPublishDirectory":"PreserveNewest","OriginalItemSpec":"wwwroot\\assets\\img\\post-bg.jpg","FileLength":1803228,"LastWriteTime":"2023-12-06T10:46:11+00:00"},"n6Lie8MBwDuCSTgT9iZX7sw\u002Bv6RqSqjHJoDoM1tp0yo=":{"Identity":"C:\\Users\\phamn\\Desktop\\Code\\TrungWebAPI\\src\\WebApp\\wwwroot\\assets\\img\\post-sample-image.jpg","SourceId":"WebApp","SourceType":"Discovered","ContentRoot":"C:\\Users\\phamn\\Desktop\\Code\\TrungWebAPI\\src\\WebApp\\wwwroot\\","BasePath":"/","RelativePath":"assets/img/post-sample-image#[.{fingerprint}]?.jpg","AssetKind":"All","AssetMode":"All","AssetRole":"Primary","AssetMergeBehavior":null,"AssetMergeSource":"","RelatedAsset":null,"AssetTraitName":null,"AssetTraitValue":null,"Fingerprint":"jcy7qsp5x5","Integrity":"o8Nuw0Y6qkUDRZxa/ZofKUYBRNkOSI1vulaEXI6yF54=","CopyToOutputDirectory":"Never","CopyToPublishDirectory":"PreserveNewest","OriginalItemSpec":"wwwroot\\assets\\img\\post-sample-image.jpg","FileLength":115144,"LastWriteTime":"2023-12-06T10:46:11+00:00"},"g5l7uZuCWTEhSH7yjma4hqv2mxWRsb/slvVAjFRyDdo=":{"Identity":"C:\\Users\\phamn\\Desktop\\Code\\TrungWebAPI\\src\\WebApp\\wwwroot\\css\\styles.css","SourceId":"WebApp","SourceType":"Discovered","ContentRoot":"C:\\Users\\phamn\\Desktop\\Code\\TrungWebAPI\\src\\WebApp\\wwwroot\\","BasePath":"/","RelativePath":"css/styles#[.{fingerprint}]?.css","AssetKind":"All","AssetMode":"All","AssetRole":"Primary","AssetMergeBehavior":null,"AssetMergeSource":"","RelatedAsset":null,"AssetTraitName":null,"AssetTraitValue":null,"Fingerprint":"02don332pa","Integrity":"GGvJMKGsdOcjQG20pQn8\u002BulhpTrmbhoK8jc4I7YcSew=","CopyToOutputDirectory":"Never","CopyToPublishDirectory":"PreserveNewest","OriginalItemSpec":"wwwroot\\css\\styles.css","FileLength":233159,"LastWriteTime":"2023-12-06T10:46:11+00:00"},"0nGuzkQyBrALhPlZNzwT6CP3vYIwKFF01NeY843K4Ag=":{"Identity":"C:\\Users\\phamn\\Desktop\\Code\\TrungWebAPI\\src\\WebApp\\wwwroot\\js\\scripts.js","SourceId":"WebApp","SourceType":"Discovered","ContentRoot":"C:\\Users\\phamn\\Desktop\\Code\\TrungWebAPI\\src\\WebApp\\wwwroot\\","BasePath":"/","RelativePath":"js/scripts#[.{fingerprint}]?.js","AssetKind":"All","AssetMode":"All","AssetRole":"Primary","AssetMergeBehavior":null,"AssetMergeSource":"","RelatedAsset":null,"AssetTraitName":null,"AssetTraitValue":null,"Fingerprint":"ow7vr36ags","Integrity":"OP88aJC5UdClVfW0oioWa\u002BJS\u002BC1b/TpKsCc4ZWtAFDI=","CopyToOutputDirectory":"Never","CopyToPublishDirectory":"PreserveNewest","OriginalItemSpec":"wwwroot\\js\\scripts.js","FileLength":1176,"LastWriteTime":"2023-12-06T10:46:11+00:00"}},"CachedCopyCandidates":{}}